neurohab/__init__.py
neurohab/neurohab.py
neurohab-0.0.2.dist-info/LICENSE
neurohab-0.0.2.dist-info/METADATA
neurohab-0.0.2.dist-info/WHEEL
neurohab-0.0.2.dist-info/top_level.txt
neurohab-0.0.2.dist-info/RECORD
