Metadata-Version: 2.1
Name: neurohab
Version: 0.0.2
Summary: Voxelwise brain habituation
Home-page: https://github.com/fcalesella/neurohab
Author: Federico Calesella
Author-email: f.calesella@gmail.com
License: GNU General Public License v3.0
License-File: LICENSE
Requires-Dist: numpy
Requires-Dist: nibabel
Requires-Dist: scipy
